pipegen/__init__.py
pipegen/args.py
pipegen/cli.py
pipegen/config.py
pipegen/schema.py
pipegen/generators/__init__.py
pipegen/generators/codebuild.py
pipegen/generators/codepipeline.py
pipegen/generators/iam.py
pipegen/generators/interfaces.py
pipegen/generators/logs.py
pipegen-0.5.0.dist-info/LICENSE
pipegen-0.5.0.dist-info/METADATA
pipegen-0.5.0.dist-info/WHEEL
pipegen-0.5.0.dist-info/entry_points.txt
pipegen-0.5.0.dist-info/top_level.txt
pipegen-0.5.0.dist-info/RECORD
