Metadata-Version: 2.1
Name: pipegen
Version: 0.5.0
Summary: CodePipeline Generator
Author: Sam Jarrett
Author-email: sam@samjarrett.com.au
License: MIT
Classifier: License :: OSI Approved :: MIT License
Classifier: Programming Language :: Python
Classifier: Programming Language :: Python :: 3
Classifier: Programming Language :: Python :: 3.8
Classifier: Programming Language :: Python :: 3.9
Classifier: Programming Language :: Python :: 3.10
Requires-Python: >=3.8
License-File: LICENSE
Requires-Dist: cfn-sync (>=0.0.9)
Requires-Dist: boto3
Requires-Dist: strictyaml
Requires-Dist: jinja2 (>=2.0.0)
Requires-Dist: click (>=7.0.0)
